repo2notebook.py
repo2notebook-1.0.0.dist-info/licenses/LICENSE
repo2notebook-1.0.0.dist-info/METADATA
repo2notebook-1.0.0.dist-info/WHEEL
repo2notebook-1.0.0.dist-info/entry_points.txt
repo2notebook-1.0.0.dist-info/top_level.txt
repo2notebook-1.0.0.dist-info/RECORD
