Metadata-Version: 2.4
Name: repo2notebook
Version: 1.0.0
Summary: Convert any code repository into a single markdown file for NotebookLM
Author: Appaholics
License: MIT
Project-URL: Homepage, https://github.com/Appaholics/repo2notebook
Project-URL: Repository, https://github.com/Appaholics/repo2notebook
Project-URL: Issues, https://github.com/Appaholics/repo2notebook/issues
Keywords: notebooklm,llm,markdown,code,repository,converter
Classifier: Development Status :: 4 - Beta
Classifier: Environment :: Console
Classifier: Intended Audience :: Developers
Classifier: License :: OSI Approved :: MIT License
Classifier: Operating System :: OS Independent
Classifier: Programming Language :: Python :: 3
Classifier: Programming Language :: Python :: 3.9
Classifier: Programming Language :: Python :: 3.10
Classifier: Programming Language :: Python :: 3.11
Classifier: Programming Language :: Python :: 3.12
Classifier: Topic :: Software Development :: Documentation
Classifier: Topic :: Text Processing :: Markup :: Markdown
Requires-Python: >=3.9
License-File: LICENSE
Dynamic: license-file
